instagram_osint/__init__.py
instagram_osint/cli.py
instagram_osint/instagramOSINT.py
instagram_osint-1.1.3.dist-info/licenses/LICENSE
instagram_osint-1.1.3.dist-info/METADATA
instagram_osint-1.1.3.dist-info/WHEEL
instagram_osint-1.1.3.dist-info/entry_points.txt
instagram_osint-1.1.3.dist-info/top_level.txt
instagram_osint-1.1.3.dist-info/RECORD
