Metadata-Version: 2.4
Name: instagram_osint
Version: 1.1.3
Summary: A powerful Instagram scraping and OSINT utility
Home-page: https://github.com/sudo-junaiddev/fork-InstagramOSINT
Author: Junaid
Author-email: contact@abujuni.dev
License: MIT
Project-URL: Bug Reports, https://github.com/sudo-junaiddev/fork-InstagramOSINT/issues
Project-URL: Source, https://github.com/sudo-junaiddev/fork-InstagramOSINT
Project-URL: Documentation, https://github.com/sudo-junaiddev/fork-InstagramOSINT#readme
Keywords: instagram osint scraper social-media intelligence
Classifier: Development Status :: 4 - Beta
Classifier: Intended Audience :: Developers
Classifier: Intended Audience :: Information Technology
Classifier: Topic :: Security
Classifier: Topic :: Internet :: WWW/HTTP :: Dynamic Content
Classifier: License :: OSI Approved :: MIT License
Classifier: Programming Language :: Python :: 3
Classifier: Programming Language :: Python :: 3.7
Classifier: Programming Language :: Python :: 3.8
Classifier: Programming Language :: Python :: 3.9
Classifier: Programming Language :: Python :: 3.10
Classifier: Programming Language :: Python :: 3.11
Requires-Python: >=3.7
License-File: LICENSE
Requires-Dist: requests>=2.28.0
Requires-Dist: beautifulsoup4>=4.11.0
Dynamic: author
Dynamic: author-email
Dynamic: classifier
Dynamic: description
Dynamic: description-content-type
Dynamic: home-page
Dynamic: keywords
Dynamic: license
Dynamic: license-file
Dynamic: project-url
Dynamic: requires-dist
Dynamic: requires-python
Dynamic: summary
